{
  "Children": null,
  "DisplayInMenu": false,
  "ParentPageId": -1,
  "DisplayAfter": null,
  "RecordNamePropertyId": 11,
  "UpdateRecordNameProperty": null,
  "ShowDashboardModule": false,
  "Properties": null,
  "RolePermissions": null,
  "Id": 6,
  "GlobalId": "2ade721a-ae65-449c-b61a-1c4955901aeb",
  "VersionId": 6,
  "EntityTabId": 54,
  "Name": "Activity",
  "PluralName": "Activities",
  "PageUiLibrary": 2,
  "CreatedDate": "2021-10-27T10:22:21.43",
  "CreatedBy": "SuperUser Account",
  "LastModifiedBy": "SuperUser Account",
  "LastModifiedOn": "2022-04-15T11:50:02.0666667",
  "Icon": "table",
  "Type": 0,
  "BuiltInType": null,
  "EnableIndexing": false,
  "NamespaceUid": "8098259e-211f-491a-b2c3-4f12861210ad"
}